cyberpunk/__init__.py
cyberpunk/cache.py
cyberpunk/config.py
cyberpunk/cyberpunk_endpoint.py
cyberpunk/exceptions.py
cyberpunk/logger_config.py
cyberpunk/processing.py
cyberpunk/response.py
cyberpunk/server.py
cyberpunk/storage/__init__.py
cyberpunk/storage/audius.py
cyberpunk/storage/gcs.py
cyberpunk/storage/http.py
cyberpunk/storage/local.py
cyberpunk/storage/s3.py
cyberpunk/transformations/__init__.py
cyberpunk/transformations/concat.py
cyberpunk/transformations/fade_in.py
cyberpunk/transformations/fade_out.py
cyberpunk/transformations/repeat.py
cyberpunk/transformations/reverse.py
cyberpunk/transformations/slice.py
cyberpunk-0.2.7.dist-info/entry_points.txt
cyberpunk-0.2.7.dist-info/LICENSE
cyberpunk-0.2.7.dist-info/WHEEL
cyberpunk-0.2.7.dist-info/METADATA
cyberpunk-0.2.7.dist-info/RECORD
