Metadata-Version: 2.1
Name: cyberpunk
Version: 0.2.7
Summary: Audio Processing Server
Home-page: https://github.com/jonaylor89/cyberpunk
Keywords: audio,sound,server
Author: Johannes Naylor
Author-email: jonaylor89@gmail.com
Requires-Python: >=3.9,<4.0
Classifier: Programming Language :: Python :: 3
Classifier: Programming Language :: Python :: 3.10
Classifier: Programming Language :: Python :: 3.9
Requires-Dist: Flask (>=2.0.2,<3.0.0)
Requires-Dist: PyYAML (>=6.0,<7.0)
Requires-Dist: boto3 (>=1.20.54,<2.0.0)
Requires-Dist: click (>=8.0.3,<9.0.0)
Requires-Dist: google-auth (>=2.6.2,<3.0.0)
Requires-Dist: google-cloud-storage (>=2.2.1,<3.0.0)
Requires-Dist: gunicorn (>=20.1.0,<21.0.0)
Requires-Dist: opentelemetry-api (>=1.10.0,<2.0.0)
Requires-Dist: opentelemetry-exporter-gcp-trace (>=1.1.0,<2.0.0)
Requires-Dist: opentelemetry-exporter-jaeger (>=1.10.0,<2.0.0)
Requires-Dist: opentelemetry-instrumentation-flask (>=0.29b0,<0.30)
Requires-Dist: opentelemetry-instrumentation-requests (>=0.29b0,<0.30)
Requires-Dist: opentelemetry-sdk (>=1.10.0,<2.0.0)
Requires-Dist: pydub (>=0.25.1,<0.26.0)
Requires-Dist: python-dotenv (>=0.19.2,<0.20.0)
Requires-Dist: requests (>=2.27.1,<3.0.0)
Project-URL: Repository, https://github.com/jonaylor89/cyberpunk
